gtnhvelo/__init__.py
gtnhvelo/__main__.py
gtnhvelo/cli.py
gtnhvelo/data/__init__.py
gtnhvelo/data/basicTypes.py
gtnhvelo/data/loadMachines.py
gtnhvelo/graph/__init__.py
gtnhvelo/graph/_backEdges.py
gtnhvelo/graph/_core.py
gtnhvelo/graph/_machineLocking.py
gtnhvelo/graph/_portNodes.py
gtnhvelo/graph/_postProcessing.py
gtnhvelo/graph/_preProcessing.py
gtnhvelo/graph/_utils.py
gtnhvelo/gtnh/__init__.py
gtnhvelo/gtnh/overclocks.py
gtnhvelo/module/__init__.py
gtnhvelo/module/flow.py
gtnhvelo/prototypes/__init__.py
gtnhvelo/prototypes/linearSolver.py
gtnhvelo/prototypes/sympy.py
gtnhvelo/resources/config_template.yaml
gtnhvelo/resources/data.yaml
gtnhvelo-0.2.0.dist-info/entry_points.txt
gtnhvelo-0.2.0.dist-info/LICENSE.txt
gtnhvelo-0.2.0.dist-info/METADATA
gtnhvelo-0.2.0.dist-info/WHEEL
gtnhvelo-0.2.0.dist-info/RECORD
