Metadata-Version: 2.1
Name: gtnhvelo
Version: 0.2.0
Summary: Factory Optimization Flowcharts for Gregtech: New Horizons
License: MIT
Author: velolib
Author-email: vlocitize@gmail.com
Requires-Python: >=3.11,<4.0
Classifier: License :: OSI Approved :: MIT License
Classifier: Programming Language :: Python :: 3
Classifier: Programming Language :: Python :: 3.11
Requires-Dist: PyYAML (>=6.0,<7.0)
Requires-Dist: graphviz (>=0.20.1,<0.21.0)
Requires-Dist: prompt-toolkit (>=3.0.36,<4.0.0)
Requires-Dist: rich (>=13.0.0,<14.0.0)
Requires-Dist: sympy (>=1.11.1,<2.0.0)
Requires-Dist: typer (>=0.7.0,<0.8.0)
